[
    {
        "eventId": 101,
        "periodDescriptor": {
            "number": 1,
            "periodType": "REG",
            "maxRegulationPeriods": 3
        },
        "timeInPeriod": "00:00",
        "timeRemaining": "20:00",
        "situationCode": "1551",
        "homeTeamDefendingSide": "left",
        "typeCode": 502,
        "typeDescKey": "faceoff",
        "sortOrder": 11,
        "details": {
            "eventOwnerTeamId": 19,
            "losingPlayerId": 8484801,
            "winningPlayerId": 8480023,
            "xCoord": 0,
            "yCoord": 0,
            "zoneCode": "N"
        }
    },
    {
        "eventId": 105,
        "periodDescriptor": {
            "number": 1,
            "periodType": "REG",
            "maxRegulationPeriods": 3
        },
        "timeInPeriod": "01:13",
        "timeRemaining": "18:47",
        "situationCode": "1551",
        "homeTeamDefendingSide": "left",
        "typeCode": 502,
        "typeDescKey": "faceoff",
        "sortOrder": 25,
        "details": {
            "eventOwnerTeamId": 28,
            "losingPlayerId": 8475170,
            "winningPlayerId": 8484227,
            "xCoord": -69,
            "yCoord": 22,
            "zoneCode": "D"
        }
    },
    {
        "eventId": 104,
        "periodDescriptor": {
            "number": 1,
            "periodType": "REG",
            "maxRegulationPeriods": 3
        },
        "timeInPeriod": "01:42",
        "timeRemaining": "18:18",
        "situationCode": "1551",
        "homeTeamDefendingSide": "left",
        "typeCode": 502,
        "typeDescKey": "faceoff",
        "sortOrder": 31,
        "details": {
            "eventOwnerTeamId": 28,
            "losingPlayerId": 8477573,
            "winningPlayerId": 8480848,
            "xCoord": 20,
            "yCoord": -22,
            "zoneCode": "N"
        }
    },
    {
        "eventId": 106,
        "periodDescriptor": {
            "number": 1,
            "periodType": "REG",
            "maxRegulationPeriods": 3
        },
        "timeInPeriod": "03:38",
        "timeRemaining": "16:22",
        "situationCode": "1551",
        "homeTeamDefendingSide": "left",
        "typeCode": 502,
        "typeDescKey": "faceoff",
        "sortOrder": 60,
        "details": {
            "eventOwnerTeamId": 19,
            "losingPlayerId": 8477505,
            "winningPlayerId": 8477402,
            "xCoord": -69,
            "yCoord": -22,
            "zoneCode": "O"
        }
    },
    {
        "eventId": 107,
        "periodDescriptor": {
            "number": 1,
            "periodType": "REG",
            "maxRegulationPeriods": 3
        },
        "timeInPeriod": "05:29",
        "timeRemaining": "14:31",
        "situationCode": "1551",
        "homeTeamDefendingSide": "left",
        "typeCode": 502,
        "typeDescKey": "faceoff",
        "sortOrder": 82,
        "details": {
            "eventOwnerTeamId": 19,
            "losingPlayerId": 8484227,
            "winningPlayerId": 8480023,
            "xCoord": -69,
            "yCoord": 22,
            "zoneCode": "O"
        }
    },
    {
        "eventId": 108,
        "periodDescriptor": {
            "number": 1,
            "periodType": "REG",
            "maxRegulationPeriods": 3
        },
        "timeInPeriod": "05:48",
        "timeRemaining": "14:12",
        "situationCode": "1551",
        "homeTeamDefendingSide": "left",
        "typeCode": 502,
        "typeDescKey": "faceoff",
        "sortOrder": 92,
        "details": {
            "eventOwnerTeamId": 19,
            "losingPlayerId": 8480848,
            "winningPlayerId": 8476889,
            "xCoord": -69,
            "yCoord": -22,
            "zoneCode": "O"
        }
    },
    {
        "eventId": 109,
        "periodDescriptor": {
            "number": 1,
            "periodType": "REG",
            "maxRegulationPeriods": 3
        },
        "timeInPeriod": "07:01",
        "timeRemaining": "12:59",
        "situationCode": "1551",
        "homeTeamDefendingSide": "left",
        "typeCode": 502,
        "typeDescKey": "faceoff",
        "sortOrder": 112,
        "details": {
            "eventOwnerTeamId": 19,
            "losingPlayerId": 8477505,
            "winningPlayerId": 8480023,
            "xCoord": 0,
            "yCoord": 0,
            "zoneCode": "N"
        }
    },
    {
        "eventId": 110,
        "periodDescriptor": {
            "number": 1,
            "periodType": "REG",
            "maxRegulationPeriods": 3
        },
        "timeInPeriod": "08:51",
        "timeRemaining": "11:09",
        "situationCode": "1551",
        "homeTeamDefendingSide": "left",
        "typeCode": 502,
        "typeDescKey": "faceoff",
        "sortOrder": 130,
        "details": {
            "eventOwnerTeamId": 19,
            "losingPlayerId": 8484227,
            "winningPlayerId": 8476889,
            "xCoord": 0,
            "yCoord": 0,
            "zoneCode": "N"
        }
    },
    {
        "eventId": 111,
        "periodDescriptor": {
            "number": 1,
            "periodType": "REG",
            "maxRegulationPeriods": 3
        },
        "timeInPeriod": "08:55",
        "timeRemaining": "11:05",
        "situationCode": "1551",
        "homeTeamDefendingSide": "left",
        "typeCode": 502,
        "typeDescKey": "faceoff",
        "sortOrder": 134,
        "details": {
            "eventOwnerTeamId": 28,
            "losingPlayerId": 8476889,
            "winningPlayerId": 8481477,
            "xCoord": 0,
            "yCoord": 0,
            "zoneCode": "N"
        }
    },
    {
        "eventId": 112,
        "periodDescriptor": {
            "number": 1,
            "periodType": "REG",
            "maxRegulationPeriods": 3
        },
        "timeInPeriod": "09:46",
        "timeRemaining": "10:14",
        "situationCode": "1551",
        "homeTeamDefendingSide": "left",
        "typeCode": 502,
        "typeDescKey": "faceoff",
        "sortOrder": 150,
        "details": {
            "eventOwnerTeamId": 19,
            "losingPlayerId": 8484227,
            "winningPlayerId": 8475170,
            "xCoord": 69,
            "yCoord": -22,
            "zoneCode": "D"
        }
    },
    {
        "eventId": 113,
        "periodDescriptor": {
            "number": 1,
            "periodType": "REG",
            "maxRegulationPeriods": 3
        },
        "timeInPeriod": "10:23",
        "timeRemaining": "09:37",
        "situationCode": "1551",
        "homeTeamDefendingSide": "left",
        "typeCode": 502,
        "typeDescKey": "faceoff",
        "sortOrder": 164,
        "details": {
            "eventOwnerTeamId": 28,
            "losingPlayerId": 8480023,
            "winningPlayerId": 8479316,
            "xCoord": 69,
            "yCoord": -22,
            "zoneCode": "O"
        }
    },
    {
        "eventId": 114,
        "periodDescriptor": {
            "number": 1,
            "periodType": "REG",
            "maxRegulationPeriods": 3
        },
        "timeInPeriod": "13:26",
        "timeRemaining": "06:34",
        "situationCode": "1551",
        "homeTeamDefendingSide": "left",
        "typeCode": 502,
        "typeDescKey": "faceoff",
        "sortOrder": 201,
        "details": {
            "eventOwnerTeamId": 28,
            "losingPlayerId": 8475170,
            "winningPlayerId": 8481477,
            "xCoord": 20,
            "yCoord": 22,
            "zoneCode": "N"
        }
    },
    {
        "eventId": 116,
        "periodDescriptor": {
            "number": 1,
            "periodType": "REG",
            "maxRegulationPeriods": 3
        },
        "timeInPeriod": "15:01",
        "timeRemaining": "04:59",
        "situationCode": "1551",
        "homeTeamDefendingSide": "left",
        "typeCode": 502,
        "typeDescKey": "faceoff",
        "sortOrder": 226,
        "details": {
            "eventOwnerTeamId": 19,
            "losingPlayerId": 8477505,
            "winningPlayerId": 8477402,
            "xCoord": -69,
            "yCoord": -22,
            "zoneCode": "O"
        }
    },
    {
        "eventId": 117,
        "periodDescriptor": {
            "number": 1,
            "periodType": "REG",
            "maxRegulationPeriods": 3
        },
        "timeInPeriod": "15:16",
        "timeRemaining": "04:44",
        "situationCode": "1551",
        "homeTeamDefendingSide": "left",
        "typeCode": 502,
        "typeDescKey": "faceoff",
        "sortOrder": 232,
        "details": {
            "eventOwnerTeamId": 28,
            "losingPlayerId": 8477402,
            "winningPlayerId": 8475798,
            "xCoord": 69,
            "yCoord": -22,
            "zoneCode": "O"
        }
    },
    {
        "eventId": 118,
        "periodDescriptor": {
            "number": 1,
            "periodType": "REG",
            "maxRegulationPeriods": 3
        },
        "timeInPeriod": "15:54",
        "timeRemaining": "04:06",
        "situationCode": "1551",
        "homeTeamDefendingSide": "left",
        "typeCode": 502,
        "typeDescKey": "faceoff",
        "sortOrder": 237,
        "details": {
            "eventOwnerTeamId": 19,
            "losingPlayerId": 8484227,
            "winningPlayerId": 8480023,
            "xCoord": -69,
            "yCoord": 22,
            "zoneCode": "O"
        }
    },
    {
        "eventId": 120,
        "periodDescriptor": {
            "number": 1,
            "periodType": "REG",
            "maxRegulationPeriods": 3
        },
        "timeInPeriod": "16:11",
        "timeRemaining": "03:49",
        "situationCode": "1551",
        "homeTeamDefendingSide": "left",
        "typeCode": 502,
        "typeDescKey": "faceoff",
        "sortOrder": 242,
        "details": {
            "eventOwnerTeamId": 19,
            "losingPlayerId": 8480848,
            "winningPlayerId": 8476889,
            "xCoord": -20,
            "yCoord": -22,
            "zoneCode": "N"
        }
    },
    {
        "eventId": 121,
        "periodDescriptor": {
            "number": 1,
            "periodType": "REG",
            "maxRegulationPeriods": 3
        },
        "timeInPeriod": "17:14",
        "timeRemaining": "02:46",
        "situationCode": "1551",
        "homeTeamDefendingSide": "left",
        "typeCode": 502,
        "typeDescKey": "faceoff",
        "sortOrder": 259,
        "details": {
            "eventOwnerTeamId": 19,
            "losingPlayerId": 8484801,
            "winningPlayerId": 8475170,
            "xCoord": 0,
            "yCoord": 0,
            "zoneCode": "N"
        }
    },
    {
        "eventId": 122,
        "periodDescriptor": {
            "number": 1,
            "periodType": "REG",
            "maxRegulationPeriods": 3
        },
        "timeInPeriod": "17:23",
        "timeRemaining": "02:37",
        "situationCode": "1551",
        "homeTeamDefendingSide": "left",
        "typeCode": 502,
        "typeDescKey": "faceoff",
        "sortOrder": 261,
        "details": {
            "eventOwnerTeamId": 19,
            "losingPlayerId": 8484801,
            "winningPlayerId": 8475170,
            "xCoord": -20,
            "yCoord": 22,
            "zoneCode": "N"
        }
    },
    {
        "eventId": 123,
        "periodDescriptor": {
            "number": 1,
            "periodType": "REG",
            "maxRegulationPeriods": 3
        },
        "timeInPeriod": "18:17",
        "timeRemaining": "01:43",
        "situationCode": "1551",
        "homeTeamDefendingSide": "left",
        "typeCode": 502,
        "typeDescKey": "faceoff",
        "sortOrder": 278,
        "details": {
            "eventOwnerTeamId": 28,
            "losingPlayerId": 8477402,
            "winningPlayerId": 8477505,
            "xCoord": -69,
            "yCoord": -22,
            "zoneCode": "D"
        }
    },
    {
        "eventId": 124,
        "periodDescriptor": {
            "number": 1,
            "periodType": "REG",
            "maxRegulationPeriods": 3
        },
        "timeInPeriod": "18:44",
        "timeRemaining": "01:16",
        "situationCode": "1551",
        "homeTeamDefendingSide": "left",
        "typeCode": 502,
        "typeDescKey": "faceoff",
        "sortOrder": 284,
        "details": {
            "eventOwnerTeamId": 19,
            "losingPlayerId": 8484227,
            "winningPlayerId": 8482077,
            "xCoord": -20,
            "yCoord": -22,
            "zoneCode": "N"
        }
    },
    {
        "eventId": 125,
        "periodDescriptor": {
            "number": 2,
            "periodType": "REG",
            "maxRegulationPeriods": 3
        },
        "timeInPeriod": "00:00",
        "timeRemaining": "20:00",
        "situationCode": "1551",
        "homeTeamDefendingSide": "right",
        "typeCode": 502,
        "typeDescKey": "faceoff",
        "sortOrder": 305,
        "details": {
            "eventOwnerTeamId": 19,
            "losingPlayerId": 8484801,
            "winningPlayerId": 8480023,
            "xCoord": 0,
            "yCoord": 0,
            "zoneCode": "N"
        }
    },
    {
        "eventId": 127,
        "periodDescriptor": {
            "number": 2,
            "periodType": "REG",
            "maxRegulationPeriods": 3
        },
        "timeInPeriod": "02:06",
        "timeRemaining": "17:54",
        "situationCode": "1551",
        "homeTeamDefendingSide": "right",
        "typeCode": 502,
        "typeDescKey": "faceoff",
        "sortOrder": 334,
        "details": {
            "eventOwnerTeamId": 28,
            "losingPlayerId": 8475170,
            "winningPlayerId": 8477505,
            "xCoord": -20,
            "yCoord": 22,
            "zoneCode": "N"
        }
    },
    {
        "eventId": 129,
        "periodDescriptor": {
            "number": 2,
            "periodType": "REG",
            "maxRegulationPeriods": 3
        },
        "timeInPeriod": "04:09",
        "timeRemaining": "15:51",
        "situationCode": "1551",
        "homeTeamDefendingSide": "right",
        "typeCode": 502,
        "typeDescKey": "faceoff",
        "sortOrder": 358,
        "details": {
            "eventOwnerTeamId": 19,
            "losingPlayerId": 8484227,
            "winningPlayerId": 8480023,
            "xCoord": -20,
            "yCoord": -22,
            "zoneCode": "N"
        }
    },
    {
        "eventId": 130,
        "periodDescriptor": {
            "number": 2,
            "periodType": "REG",
            "maxRegulationPeriods": 3
        },
        "timeInPeriod": "06:55",
        "timeRemaining": "13:05",
        "situationCode": "1551",
        "homeTeamDefendingSide": "right",
        "typeCode": 502,
        "typeDescKey": "faceoff",
        "sortOrder": 388,
        "details": {
            "eventOwnerTeamId": 19,
            "losingPlayerId": 8484801,
            "winningPlayerId": 8480023,
            "xCoord": -69,
            "yCoord": -22,
            "zoneCode": "D"
        }
    },
    {
        "eventId": 131,
        "periodDescriptor": {
            "number": 2,
            "periodType": "REG",
            "maxRegulationPeriods": 3
        },
        "timeInPeriod": "07:02",
        "timeRemaining": "12:58",
        "situationCode": "1551",
        "homeTeamDefendingSide": "right",
        "typeCode": 502,
        "typeDescKey": "faceoff",
        "sortOrder": 390,
        "details": {
            "eventOwnerTeamId": 19,
            "losingPlayerId": 8484801,
            "winningPlayerId": 8480023,
            "xCoord": 20,
            "yCoord": -22,
            "zoneCode": "N"
        }
    },
    {
        "eventId": 133,
        "periodDescriptor": {
            "number": 2,
            "periodType": "REG",
            "maxRegulationPeriods": 3
        },
        "timeInPeriod": "07:41",
        "timeRemaining": "12:19",
        "situationCode": "1551",
        "homeTeamDefendingSide": "right",
        "typeCode": 502,
        "typeDescKey": "faceoff",
        "sortOrder": 396,
        "details": {
            "eventOwnerTeamId": 28,
            "losingPlayerId": 8476889,
            "winningPlayerId": 8481477,
            "xCoord": 69,
            "yCoord": -22,
            "zoneCode": "D"
        }
    },
    {
        "eventId": 134,
        "periodDescriptor": {
            "number": 2,
            "periodType": "REG",
            "maxRegulationPeriods": 3
        },
        "timeInPeriod": "07:53",
        "timeRemaining": "12:07",
        "situationCode": "1451",
        "homeTeamDefendingSide": "right",
        "typeCode": 502,
        "typeDescKey": "faceoff",
        "sortOrder": 403,
        "details": {
            "eventOwnerTeamId": 28,
            "losingPlayerId": 8480023,
            "winningPlayerId": 8475798,
            "xCoord": -69,
            "yCoord": -22,
            "zoneCode": "O"
        }
    },
    {
        "eventId": 135,
        "periodDescriptor": {
            "number": 2,
            "periodType": "REG",
            "maxRegulationPeriods": 3
        },
        "timeInPeriod": "08:26",
        "timeRemaining": "11:34",
        "situationCode": "1551",
        "homeTeamDefendingSide": "right",
        "typeCode": 502,
        "typeDescKey": "faceoff",
        "sortOrder": 410,
        "details": {
            "eventOwnerTeamId": 19,
            "losingPlayerId": 8477505,
            "winningPlayerId": 8476889,
            "xCoord": 0,
            "yCoord": 0,
            "zoneCode": "N"
        }
    },
    {
        "eventId": 138,
        "periodDescriptor": {
            "number": 2,
            "periodType": "REG",
            "maxRegulationPeriods": 3
        },
        "timeInPeriod": "09:05",
        "timeRemaining": "10:55",
        "situationCode": "1551",
        "homeTeamDefendingSide": "right",
        "typeCode": 502,
        "typeDescKey": "faceoff",
        "sortOrder": 418,
        "details": {
            "eventOwnerTeamId": 28,
            "losingPlayerId": 8477402,
            "winningPlayerId": 8480848,
            "xCoord": 69,
            "yCoord": 22,
            "zoneCode": "D"
        }
    },
    {
        "eventId": 139,
        "periodDescriptor": {
            "number": 2,
            "periodType": "REG",
            "maxRegulationPeriods": 3
        },
        "timeInPeriod": "09:28",
        "timeRemaining": "10:32",
        "situationCode": "1551",
        "homeTeamDefendingSide": "right",
        "typeCode": 502,
        "typeDescKey": "faceoff",
        "sortOrder": 421,
        "details": {
            "eventOwnerTeamId": 19,
            "losingPlayerId": 8475798,
            "winningPlayerId": 8477402,
            "xCoord": -69,
            "yCoord": -22,
            "zoneCode": "D"
        }
    },
    {
        "eventId": 140,
        "periodDescriptor": {
            "number": 2,
            "periodType": "REG",
            "maxRegulationPeriods": 3
        },
        "timeInPeriod": "09:35",
        "timeRemaining": "10:25",
        "situationCode": "1551",
        "homeTeamDefendingSide": "right",
        "typeCode": 502,
        "typeDescKey": "faceoff",
        "sortOrder": 423,
        "details": {
            "eventOwnerTeamId": 19,
            "losingPlayerId": 8484227,
            "winningPlayerId": 8477402,
            "xCoord": -69,
            "yCoord": 22,
            "zoneCode": "D"
        }
    },
    {
        "eventId": 141,
        "periodDescriptor": {
            "number": 2,
            "periodType": "REG",
            "maxRegulationPeriods": 3
        },
        "timeInPeriod": "09:42",
        "timeRemaining": "10:18",
        "situationCode": "1551",
        "homeTeamDefendingSide": "right",
        "typeCode": 502,
        "typeDescKey": "faceoff",
        "sortOrder": 426,
        "details": {
            "eventOwnerTeamId": 19,
            "losingPlayerId": 8484227,
            "winningPlayerId": 8477402,
            "xCoord": -69,
            "yCoord": -22,
            "zoneCode": "D"
        }
    },
    {
        "eventId": 142,
        "periodDescriptor": {
            "number": 2,
            "periodType": "REG",
            "maxRegulationPeriods": 3
        },
        "timeInPeriod": "09:51",
        "timeRemaining": "10:09",
        "situationCode": "1551",
        "homeTeamDefendingSide": "right",
        "typeCode": 502,
        "typeDescKey": "faceoff",
        "sortOrder": 428,
        "details": {
            "eventOwnerTeamId": 19,
            "losingPlayerId": 8484227,
            "winningPlayerId": 8477402,
            "xCoord": -69,
            "yCoord": 22,
            "zoneCode": "D"
        }
    },
    {
        "eventId": 143,
        "periodDescriptor": {
            "number": 2,
            "periodType": "REG",
            "maxRegulationPeriods": 3
        },
        "timeInPeriod": "10:49",
        "timeRemaining": "09:11",
        "situationCode": "1451",
        "homeTeamDefendingSide": "right",
        "typeCode": 502,
        "typeDescKey": "faceoff",
        "sortOrder": 448,
        "details": {
            "eventOwnerTeamId": 19,
            "losingPlayerId": 8484801,
            "winningPlayerId": 8480023,
            "xCoord": -69,
            "yCoord": -22,
            "zoneCode": "D"
        }
    },
    {
        "eventId": 146,
        "periodDescriptor": {
            "number": 2,
            "periodType": "REG",
            "maxRegulationPeriods": 3
        },
        "timeInPeriod": "13:15",
        "timeRemaining": "06:45",
        "situationCode": "1551",
        "homeTeamDefendingSide": "right",
        "typeCode": 502,
        "typeDescKey": "faceoff",
        "sortOrder": 478,
        "details": {
            "eventOwnerTeamId": 28,
            "losingPlayerId": 8480023,
            "winningPlayerId": 8476624,
            "xCoord": -69,
            "yCoord": -22,
            "zoneCode": "O"
        }
    },
    {
        "eventId": 147,
        "periodDescriptor": {
            "number": 2,
            "periodType": "REG",
            "maxRegulationPeriods": 3
        },
        "timeInPeriod": "15:01",
        "timeRemaining": "04:59",
        "situationCode": "1551",
        "homeTeamDefendingSide": "right",
        "typeCode": 502,
        "typeDescKey": "faceoff",
        "sortOrder": 506,
        "details": {
            "eventOwnerTeamId": 28,
            "losingPlayerId": 8475170,
            "winningPlayerId": 8475798,
            "xCoord": -69,
            "yCoord": -22,
            "zoneCode": "O"
        }
    },
    {
        "eventId": 148,
        "periodDescriptor": {
            "number": 2,
            "periodType": "REG",
            "maxRegulationPeriods": 3
        },
        "timeInPeriod": "15:30",
        "timeRemaining": "04:30",
        "situationCode": "1551",
        "homeTeamDefendingSide": "right",
        "typeCode": 502,
        "typeDescKey": "faceoff",
        "sortOrder": 515,
        "details": {
            "eventOwnerTeamId": 28,
            "losingPlayerId": 8476889,
            "winningPlayerId": 8477505,
            "xCoord": 20,
            "yCoord": -22,
            "zoneCode": "N"
        }
    },
    {
        "eventId": 149,
        "periodDescriptor": {
            "number": 2,
            "periodType": "REG",
            "maxRegulationPeriods": 3
        },
        "timeInPeriod": "16:55",
        "timeRemaining": "03:05",
        "situationCode": "1541",
        "homeTeamDefendingSide": "right",
        "typeCode": 502,
        "typeDescKey": "faceoff",
        "sortOrder": 535,
        "details": {
            "eventOwnerTeamId": 19,
            "losingPlayerId": 8481477,
            "winningPlayerId": 8480023,
            "xCoord": 69,
            "yCoord": -22,
            "zoneCode": "O"
        }
    },
    {
        "eventId": 150,
        "periodDescriptor": {
            "number": 2,
            "periodType": "REG",
            "maxRegulationPeriods": 3
        },
        "timeInPeriod": "17:37",
        "timeRemaining": "02:23",
        "situationCode": "1541",
        "homeTeamDefendingSide": "right",
        "typeCode": 502,
        "typeDescKey": "faceoff",
        "sortOrder": 545,
        "details": {
            "eventOwnerTeamId": 19,
            "losingPlayerId": 8477505,
            "winningPlayerId": 8475170,
            "xCoord": 0,
            "yCoord": 0,
            "zoneCode": "N"
        }
    },
    {
        "eventId": 501,
        "periodDescriptor": {
            "number": 3,
            "periodType": "REG",
            "maxRegulationPeriods": 3
        },
        "timeInPeriod": "00:00",
        "timeRemaining": "20:00",
        "situationCode": "1551",
        "homeTeamDefendingSide": "left",
        "typeCode": 502,
        "typeDescKey": "faceoff",
        "sortOrder": 581,
        "details": {
            "eventOwnerTeamId": 19,
            "losingPlayerId": 8484801,
            "winningPlayerId": 8480023,
            "xCoord": 0,
            "yCoord": 0,
            "zoneCode": "N"
        }
    },
    {
        "eventId": 503,
        "periodDescriptor": {
            "number": 3,
            "periodType": "REG",
            "maxRegulationPeriods": 3
        },
        "timeInPeriod": "00:17",
        "timeRemaining": "19:43",
        "situationCode": "1551",
        "homeTeamDefendingSide": "left",
        "typeCode": 502,
        "typeDescKey": "faceoff",
        "sortOrder": 583,
        "details": {
            "eventOwnerTeamId": 19,
            "losingPlayerId": 8484801,
            "winningPlayerId": 8480023,
            "xCoord": 69,
            "yCoord": 22,
            "zoneCode": "D"
        }
    },
    {
        "eventId": 504,
        "periodDescriptor": {
            "number": 3,
            "periodType": "REG",
            "maxRegulationPeriods": 3
        },
        "timeInPeriod": "00:50",
        "timeRemaining": "19:10",
        "situationCode": "1551",
        "homeTeamDefendingSide": "left",
        "typeCode": 502,
        "typeDescKey": "faceoff",
        "sortOrder": 590,
        "details": {
            "eventOwnerTeamId": 19,
            "losingPlayerId": 8477505,
            "winningPlayerId": 8477402,
            "xCoord": -69,
            "yCoord": -22,
            "zoneCode": "O"
        }
    },
    {
        "eventId": 505,
        "periodDescriptor": {
            "number": 3,
            "periodType": "REG",
            "maxRegulationPeriods": 3
        },
        "timeInPeriod": "02:54",
        "timeRemaining": "17:06",
        "situationCode": "1551",
        "homeTeamDefendingSide": "left",
        "typeCode": 502,
        "typeDescKey": "faceoff",
        "sortOrder": 618,
        "details": {
            "eventOwnerTeamId": 19,
            "losingPlayerId": 8484801,
            "winningPlayerId": 8480023,
            "xCoord": 0,
            "yCoord": 0,
            "zoneCode": "N"
        }
    },
    {
        "eventId": 506,
        "periodDescriptor": {
            "number": 3,
            "periodType": "REG",
            "maxRegulationPeriods": 3
        },
        "timeInPeriod": "05:27",
        "timeRemaining": "14:33",
        "situationCode": "1551",
        "homeTeamDefendingSide": "left",
        "typeCode": 502,
        "typeDescKey": "faceoff",
        "sortOrder": 652,
        "details": {
            "eventOwnerTeamId": 19,
            "losingPlayerId": 8480848,
            "winningPlayerId": 8476889,
            "xCoord": -69,
            "yCoord": -22,
            "zoneCode": "O"
        }
    },
    {
        "eventId": 507,
        "periodDescriptor": {
            "number": 3,
            "periodType": "REG",
            "maxRegulationPeriods": 3
        },
        "timeInPeriod": "05:39",
        "timeRemaining": "14:21",
        "situationCode": "1551",
        "homeTeamDefendingSide": "left",
        "typeCode": 502,
        "typeDescKey": "faceoff",
        "sortOrder": 657,
        "details": {
            "eventOwnerTeamId": 28,
            "losingPlayerId": 8476889,
            "winningPlayerId": 8481477,
            "xCoord": 20,
            "yCoord": 22,
            "zoneCode": "N"
        }
    },
    {
        "eventId": 508,
        "periodDescriptor": {
            "number": 3,
            "periodType": "REG",
            "maxRegulationPeriods": 3
        },
        "timeInPeriod": "06:11",
        "timeRemaining": "13:49",
        "situationCode": "1551",
        "homeTeamDefendingSide": "left",
        "typeCode": 502,
        "typeDescKey": "faceoff",
        "sortOrder": 662,
        "details": {
            "eventOwnerTeamId": 19,
            "losingPlayerId": 8484801,
            "winningPlayerId": 8480023,
            "xCoord": 0,
            "yCoord": 0,
            "zoneCode": "N"
        }
    },
    {
        "eventId": 509,
        "periodDescriptor": {
            "number": 3,
            "periodType": "REG",
            "maxRegulationPeriods": 3
        },
        "timeInPeriod": "06:52",
        "timeRemaining": "13:08",
        "situationCode": "1551",
        "homeTeamDefendingSide": "left",
        "typeCode": 502,
        "typeDescKey": "faceoff",
        "sortOrder": 670,
        "details": {
            "eventOwnerTeamId": 28,
            "losingPlayerId": 8477402,
            "winningPlayerId": 8484801,
            "xCoord": -69,
            "yCoord": -22,
            "zoneCode": "D"
        }
    },
    {
        "eventId": 510,
        "periodDescriptor": {
            "number": 3,
            "periodType": "REG",
            "maxRegulationPeriods": 3
        },
        "timeInPeriod": "07:14",
        "timeRemaining": "12:46",
        "situationCode": "1551",
        "homeTeamDefendingSide": "left",
        "typeCode": 502,
        "typeDescKey": "faceoff",
        "sortOrder": 677,
        "details": {
            "eventOwnerTeamId": 19,
            "losingPlayerId": 8484227,
            "winningPlayerId": 8476889,
            "xCoord": 69,
            "yCoord": -22,
            "zoneCode": "D"
        }
    },
    {
        "eventId": 511,
        "periodDescriptor": {
            "number": 3,
            "periodType": "REG",
            "maxRegulationPeriods": 3
        },
        "timeInPeriod": "07:21",
        "timeRemaining": "12:39",
        "situationCode": "1551",
        "homeTeamDefendingSide": "left",
        "typeCode": 502,
        "typeDescKey": "faceoff",
        "sortOrder": 679,
        "details": {
            "eventOwnerTeamId": 28,
            "losingPlayerId": 8476889,
            "winningPlayerId": 8475798,
            "xCoord": 69,
            "yCoord": 22,
            "zoneCode": "O"
        }
    },
    {
        "eventId": 512,
        "periodDescriptor": {
            "number": 3,
            "periodType": "REG",
            "maxRegulationPeriods": 3
        },
        "timeInPeriod": "08:20",
        "timeRemaining": "11:40",
        "situationCode": "1551",
        "homeTeamDefendingSide": "left",
        "typeCode": 502,
        "typeDescKey": "faceoff",
        "sortOrder": 692,
        "details": {
            "eventOwnerTeamId": 28,
            "losingPlayerId": 8482077,
            "winningPlayerId": 8477505,
            "xCoord": 69,
            "yCoord": 22,
            "zoneCode": "O"
        }
    },
    {
        "eventId": 513,
        "periodDescriptor": {
            "number": 3,
            "periodType": "REG",
            "maxRegulationPeriods": 3
        },
        "timeInPeriod": "08:36",
        "timeRemaining": "11:24",
        "situationCode": "1551",
        "homeTeamDefendingSide": "left",
        "typeCode": 502,
        "typeDescKey": "faceoff",
        "sortOrder": 696,
        "details": {
            "eventOwnerTeamId": 19,
            "losingPlayerId": 8484801,
            "winningPlayerId": 8482077,
            "xCoord": 69,
            "yCoord": 22,
            "zoneCode": "D"
        }
    },
    {
        "eventId": 514,
        "periodDescriptor": {
            "number": 3,
            "periodType": "REG",
            "maxRegulationPeriods": 3
        },
        "timeInPeriod": "10:07",
        "timeRemaining": "09:53",
        "situationCode": "1541",
        "homeTeamDefendingSide": "left",
        "typeCode": 502,
        "typeDescKey": "faceoff",
        "sortOrder": 722,
        "details": {
            "eventOwnerTeamId": 28,
            "losingPlayerId": 8480023,
            "winningPlayerId": 8475798,
            "xCoord": -69,
            "yCoord": 22,
            "zoneCode": "D"
        }
    },
    {
        "eventId": 516,
        "periodDescriptor": {
            "number": 3,
            "periodType": "REG",
            "maxRegulationPeriods": 3
        },
        "timeInPeriod": "13:14",
        "timeRemaining": "06:46",
        "situationCode": "1551",
        "homeTeamDefendingSide": "left",
        "typeCode": 502,
        "typeDescKey": "faceoff",
        "sortOrder": 755,
        "details": {
            "eventOwnerTeamId": 28,
            "losingPlayerId": 8480023,
            "winningPlayerId": 8475798,
            "xCoord": 69,
            "yCoord": -22,
            "zoneCode": "O"
        }
    },
    {
        "eventId": 517,
        "periodDescriptor": {
            "number": 3,
            "periodType": "REG",
            "maxRegulationPeriods": 3
        },
        "timeInPeriod": "14:02",
        "timeRemaining": "05:58",
        "situationCode": "1551",
        "homeTeamDefendingSide": "left",
        "typeCode": 502,
        "typeDescKey": "faceoff",
        "sortOrder": 766,
        "details": {
            "eventOwnerTeamId": 28,
            "losingPlayerId": 8477402,
            "winningPlayerId": 8476624,
            "xCoord": 69,
            "yCoord": 22,
            "zoneCode": "O"
        }
    },
    {
        "eventId": 518,
        "periodDescriptor": {
            "number": 3,
            "periodType": "REG",
            "maxRegulationPeriods": 3
        },
        "timeInPeriod": "17:24",
        "timeRemaining": "02:36",
        "situationCode": "1551",
        "homeTeamDefendingSide": "left",
        "typeCode": 502,
        "typeDescKey": "faceoff",
        "sortOrder": 813,
        "details": {
            "eventOwnerTeamId": 28,
            "losingPlayerId": 8482077,
            "winningPlayerId": 8475798,
            "xCoord": 0,
            "yCoord": 0,
            "zoneCode": "N"
        }
    },
    {
        "eventId": 519,
        "periodDescriptor": {
            "number": 3,
            "periodType": "REG",
            "maxRegulationPeriods": 3
        },
        "timeInPeriod": "17:30",
        "timeRemaining": "02:30",
        "situationCode": "0651",
        "homeTeamDefendingSide": "left",
        "typeCode": 502,
        "typeDescKey": "faceoff",
        "sortOrder": 816,
        "details": {
            "eventOwnerTeamId": 28,
            "losingPlayerId": 8480023,
            "winningPlayerId": 8475798,
            "xCoord": -69,
            "yCoord": 22,
            "zoneCode": "D"
        }
    },
    {
        "eventId": 520,
        "periodDescriptor": {
            "number": 3,
            "periodType": "REG",
            "maxRegulationPeriods": 3
        },
        "timeInPeriod": "18:07",
        "timeRemaining": "01:53",
        "situationCode": "0651",
        "homeTeamDefendingSide": "left",
        "typeCode": 502,
        "typeDescKey": "faceoff",
        "sortOrder": 821,
        "details": {
            "eventOwnerTeamId": 19,
            "losingPlayerId": 8477505,
            "winningPlayerId": 8475170,
            "xCoord": -69,
            "yCoord": -22,
            "zoneCode": "O"
        }
    },
    {
        "eventId": 521,
        "periodDescriptor": {
            "number": 3,
            "periodType": "REG",
            "maxRegulationPeriods": 3
        },
        "timeInPeriod": "18:18",
        "timeRemaining": "01:42",
        "situationCode": "0651",
        "homeTeamDefendingSide": "left",
        "typeCode": 502,
        "typeDescKey": "faceoff",
        "sortOrder": 824,
        "details": {
            "eventOwnerTeamId": 28,
            "losingPlayerId": 8475170,
            "winningPlayerId": 8476624,
            "xCoord": -69,
            "yCoord": -22,
            "zoneCode": "D"
        }
    },
    {
        "eventId": 522,
        "periodDescriptor": {
            "number": 3,
            "periodType": "REG",
            "maxRegulationPeriods": 3
        },
        "timeInPeriod": "19:13",
        "timeRemaining": "00:47",
        "situationCode": "1551",
        "homeTeamDefendingSide": "left",
        "typeCode": 502,
        "typeDescKey": "faceoff",
        "sortOrder": 830,
        "details": {
            "eventOwnerTeamId": 28,
            "losingPlayerId": 8476889,
            "winningPlayerId": 8475798,
            "xCoord": 0,
            "yCoord": 0,
            "zoneCode": "N"
        }
    },
    {
        "eventId": 523,
        "periodDescriptor": {
            "number": 4,
            "periodType": "OT",
            "maxRegulationPeriods": 3
        },
        "timeInPeriod": "00:00",
        "timeRemaining": "05:00",
        "situationCode": "1331",
        "homeTeamDefendingSide": "right",
        "typeCode": 502,
        "typeDescKey": "faceoff",
        "sortOrder": 840,
        "details": {
            "eventOwnerTeamId": 19,
            "losingPlayerId": 8484801,
            "winningPlayerId": 8480023,
            "xCoord": 0,
            "yCoord": 0,
            "zoneCode": "N"
        }
    }
]