[
    {
        "eventId": 8,
        "periodDescriptor": {
            "number": 1,
            "periodType": "REG",
            "maxRegulationPeriods": 3
        },
        "timeInPeriod": "00:00",
        "timeRemaining": "20:00",
        "situationCode": "1551",
        "homeTeamDefendingSide": "right",
        "typeCode": 502,
        "typeDescKey": "faceoff",
        "sortOrder": 11,
        "details": {
            "eventOwnerTeamId": 52,
            "losingPlayerId": 8476889,
            "winningPlayerId": 8476480,
            "xCoord": 0,
            "yCoord": 0,
            "zoneCode": "N"
        }
    },
    {
        "eventId": 11,
        "periodDescriptor": {
            "number": 1,
            "periodType": "REG",
            "maxRegulationPeriods": 3
        },
        "timeInPeriod": "01:09",
        "timeRemaining": "18:51",
        "situationCode": "1551",
        "homeTeamDefendingSide": "right",
        "typeCode": 502,
        "typeDescKey": "faceoff",
        "sortOrder": 33,
        "details": {
            "eventOwnerTeamId": 19,
            "losingPlayerId": 8476392,
            "winningPlayerId": 8475170,
            "xCoord": -69,
            "yCoord": 22,
            "zoneCode": "D"
        }
    },
    {
        "eventId": 13,
        "periodDescriptor": {
            "number": 1,
            "periodType": "REG",
            "maxRegulationPeriods": 3
        },
        "timeInPeriod": "01:26",
        "timeRemaining": "18:34",
        "situationCode": "1551",
        "homeTeamDefendingSide": "right",
        "typeCode": 502,
        "typeDescKey": "faceoff",
        "sortOrder": 38,
        "details": {
            "eventOwnerTeamId": 52,
            "losingPlayerId": 8476897,
            "winningPlayerId": 8479994,
            "xCoord": -69,
            "yCoord": -22,
            "zoneCode": "O"
        }
    },
    {
        "eventId": 15,
        "periodDescriptor": {
            "number": 1,
            "periodType": "REG",
            "maxRegulationPeriods": 3
        },
        "timeInPeriod": "01:31",
        "timeRemaining": "18:29",
        "situationCode": "1551",
        "homeTeamDefendingSide": "right",
        "typeCode": 502,
        "typeDescKey": "faceoff",
        "sortOrder": 41,
        "details": {
            "eventOwnerTeamId": 52,
            "losingPlayerId": 8476897,
            "winningPlayerId": 8480289,
            "xCoord": -69,
            "yCoord": 22,
            "zoneCode": "O"
        }
    },
    {
        "eventId": 17,
        "periodDescriptor": {
            "number": 1,
            "periodType": "REG",
            "maxRegulationPeriods": 3
        },
        "timeInPeriod": "03:51",
        "timeRemaining": "16:09",
        "situationCode": "1551",
        "homeTeamDefendingSide": "right",
        "typeCode": 502,
        "typeDescKey": "faceoff",
        "sortOrder": 74,
        "details": {
            "eventOwnerTeamId": 52,
            "losingPlayerId": 8480023,
            "winningPlayerId": 8476460,
            "xCoord": 69,
            "yCoord": -22,
            "zoneCode": "D"
        }
    },
    {
        "eventId": 19,
        "periodDescriptor": {
            "number": 1,
            "periodType": "REG",
            "maxRegulationPeriods": 3
        },
        "timeInPeriod": "04:12",
        "timeRemaining": "15:48",
        "situationCode": "1551",
        "homeTeamDefendingSide": "right",
        "typeCode": 502,
        "typeDescKey": "faceoff",
        "sortOrder": 81,
        "details": {
            "eventOwnerTeamId": 19,
            "losingPlayerId": 8476460,
            "winningPlayerId": 8475170,
            "xCoord": -69,
            "yCoord": 22,
            "zoneCode": "D"
        }
    },
    {
        "eventId": 21,
        "periodDescriptor": {
            "number": 1,
            "periodType": "REG",
            "maxRegulationPeriods": 3
        },
        "timeInPeriod": "05:24",
        "timeRemaining": "14:36",
        "situationCode": "1551",
        "homeTeamDefendingSide": "right",
        "typeCode": 502,
        "typeDescKey": "faceoff",
        "sortOrder": 99,
        "details": {
            "eventOwnerTeamId": 19,
            "losingPlayerId": 8476480,
            "winningPlayerId": 8476897,
            "xCoord": -20,
            "yCoord": 22,
            "zoneCode": "N"
        }
    },
    {
        "eventId": 23,
        "periodDescriptor": {
            "number": 1,
            "periodType": "REG",
            "maxRegulationPeriods": 3
        },
        "timeInPeriod": "06:15",
        "timeRemaining": "13:45",
        "situationCode": "1551",
        "homeTeamDefendingSide": "right",
        "typeCode": 502,
        "typeDescKey": "faceoff",
        "sortOrder": 106,
        "details": {
            "eventOwnerTeamId": 52,
            "losingPlayerId": 8476897,
            "winningPlayerId": 8476460,
            "xCoord": -69,
            "yCoord": 22,
            "zoneCode": "O"
        }
    },
    {
        "eventId": 25,
        "periodDescriptor": {
            "number": 1,
            "periodType": "REG",
            "maxRegulationPeriods": 3
        },
        "timeInPeriod": "07:54",
        "timeRemaining": "12:06",
        "situationCode": "1551",
        "homeTeamDefendingSide": "right",
        "typeCode": 502,
        "typeDescKey": "faceoff",
        "sortOrder": 126,
        "details": {
            "eventOwnerTeamId": 52,
            "losingPlayerId": 8475170,
            "winningPlayerId": 8476460,
            "xCoord": -69,
            "yCoord": 22,
            "zoneCode": "O"
        }
    },
    {
        "eventId": 27,
        "periodDescriptor": {
            "number": 1,
            "periodType": "REG",
            "maxRegulationPeriods": 3
        },
        "timeInPeriod": "10:54",
        "timeRemaining": "09:06",
        "situationCode": "1551",
        "homeTeamDefendingSide": "right",
        "typeCode": 502,
        "typeDescKey": "faceoff",
        "sortOrder": 167,
        "details": {
            "eventOwnerTeamId": 19,
            "losingPlayerId": 8476480,
            "winningPlayerId": 8476889,
            "xCoord": -69,
            "yCoord": -22,
            "zoneCode": "D"
        }
    },
    {
        "eventId": 29,
        "periodDescriptor": {
            "number": 1,
            "periodType": "REG",
            "maxRegulationPeriods": 3
        },
        "timeInPeriod": "13:32",
        "timeRemaining": "06:28",
        "situationCode": "1551",
        "homeTeamDefendingSide": "right",
        "typeCode": 502,
        "typeDescKey": "faceoff",
        "sortOrder": 201,
        "details": {
            "eventOwnerTeamId": 52,
            "losingPlayerId": 8476897,
            "winningPlayerId": 8476392,
            "xCoord": -69,
            "yCoord": -22,
            "zoneCode": "O"
        }
    },
    {
        "eventId": 31,
        "periodDescriptor": {
            "number": 1,
            "periodType": "REG",
            "maxRegulationPeriods": 3
        },
        "timeInPeriod": "13:36",
        "timeRemaining": "06:24",
        "situationCode": "1551",
        "homeTeamDefendingSide": "right",
        "typeCode": 502,
        "typeDescKey": "faceoff",
        "sortOrder": 205,
        "details": {
            "eventOwnerTeamId": 19,
            "losingPlayerId": 8479293,
            "winningPlayerId": 8475170,
            "xCoord": -69,
            "yCoord": -22,
            "zoneCode": "D"
        }
    },
    {
        "eventId": 33,
        "periodDescriptor": {
            "number": 1,
            "periodType": "REG",
            "maxRegulationPeriods": 3
        },
        "timeInPeriod": "14:17",
        "timeRemaining": "05:43",
        "situationCode": "1551",
        "homeTeamDefendingSide": "right",
        "typeCode": 502,
        "typeDescKey": "faceoff",
        "sortOrder": 216,
        "details": {
            "eventOwnerTeamId": 52,
            "losingPlayerId": 8476889,
            "winningPlayerId": 8476480,
            "xCoord": 69,
            "yCoord": 22,
            "zoneCode": "D"
        }
    },
    {
        "eventId": 35,
        "periodDescriptor": {
            "number": 1,
            "periodType": "REG",
            "maxRegulationPeriods": 3
        },
        "timeInPeriod": "15:54",
        "timeRemaining": "04:06",
        "situationCode": "1551",
        "homeTeamDefendingSide": "right",
        "typeCode": 502,
        "typeDescKey": "faceoff",
        "sortOrder": 238,
        "details": {
            "eventOwnerTeamId": 19,
            "losingPlayerId": 8481019,
            "winningPlayerId": 8475170,
            "xCoord": -69,
            "yCoord": 22,
            "zoneCode": "D"
        }
    },
    {
        "eventId": 501,
        "periodDescriptor": {
            "number": 1,
            "periodType": "REG",
            "maxRegulationPeriods": 3
        },
        "timeInPeriod": "16:33",
        "timeRemaining": "03:27",
        "situationCode": "1551",
        "homeTeamDefendingSide": "right",
        "typeCode": 502,
        "typeDescKey": "faceoff",
        "sortOrder": 244,
        "details": {
            "eventOwnerTeamId": 19,
            "losingPlayerId": 8476392,
            "winningPlayerId": 8475170,
            "xCoord": 0,
            "yCoord": 0,
            "zoneCode": "N"
        }
    },
    {
        "eventId": 38,
        "periodDescriptor": {
            "number": 1,
            "periodType": "REG",
            "maxRegulationPeriods": 3
        },
        "timeInPeriod": "19:02",
        "timeRemaining": "00:58",
        "situationCode": "1551",
        "homeTeamDefendingSide": "right",
        "typeCode": 502,
        "typeDescKey": "faceoff",
        "sortOrder": 267,
        "details": {
            "eventOwnerTeamId": 52,
            "losingPlayerId": 8476889,
            "winningPlayerId": 8476460,
            "xCoord": -69,
            "yCoord": 22,
            "zoneCode": "O"
        }
    },
    {
        "eventId": 44,
        "periodDescriptor": {
            "number": 2,
            "periodType": "REG",
            "maxRegulationPeriods": 3
        },
        "timeInPeriod": "00:00",
        "timeRemaining": "20:00",
        "situationCode": "1551",
        "homeTeamDefendingSide": "left",
        "typeCode": 502,
        "typeDescKey": "faceoff",
        "sortOrder": 279,
        "details": {
            "eventOwnerTeamId": 19,
            "losingPlayerId": 8476460,
            "winningPlayerId": 8480023,
            "xCoord": 0,
            "yCoord": 0,
            "zoneCode": "N"
        }
    },
    {
        "eventId": 47,
        "periodDescriptor": {
            "number": 2,
            "periodType": "REG",
            "maxRegulationPeriods": 3
        },
        "timeInPeriod": "00:22",
        "timeRemaining": "19:38",
        "situationCode": "1551",
        "homeTeamDefendingSide": "left",
        "typeCode": 502,
        "typeDescKey": "faceoff",
        "sortOrder": 286,
        "details": {
            "eventOwnerTeamId": 19,
            "losingPlayerId": 8476480,
            "winningPlayerId": 8476889,
            "xCoord": 69,
            "yCoord": -22,
            "zoneCode": "D"
        }
    },
    {
        "eventId": 49,
        "periodDescriptor": {
            "number": 2,
            "periodType": "REG",
            "maxRegulationPeriods": 3
        },
        "timeInPeriod": "01:02",
        "timeRemaining": "18:58",
        "situationCode": "1551",
        "homeTeamDefendingSide": "left",
        "typeCode": 502,
        "typeDescKey": "faceoff",
        "sortOrder": 299,
        "details": {
            "eventOwnerTeamId": 19,
            "losingPlayerId": 8476392,
            "winningPlayerId": 8475170,
            "xCoord": -20,
            "yCoord": -22,
            "zoneCode": "N"
        }
    },
    {
        "eventId": 502,
        "periodDescriptor": {
            "number": 2,
            "periodType": "REG",
            "maxRegulationPeriods": 3
        },
        "timeInPeriod": "02:34",
        "timeRemaining": "17:26",
        "situationCode": "1551",
        "homeTeamDefendingSide": "left",
        "typeCode": 502,
        "typeDescKey": "faceoff",
        "sortOrder": 314,
        "details": {
            "eventOwnerTeamId": 19,
            "losingPlayerId": 8476460,
            "winningPlayerId": 8480023,
            "xCoord": 0,
            "yCoord": 0,
            "zoneCode": "N"
        }
    },
    {
        "eventId": 503,
        "periodDescriptor": {
            "number": 2,
            "periodType": "REG",
            "maxRegulationPeriods": 3
        },
        "timeInPeriod": "03:01",
        "timeRemaining": "16:59",
        "situationCode": "1551",
        "homeTeamDefendingSide": "left",
        "typeCode": 502,
        "typeDescKey": "faceoff",
        "sortOrder": 320,
        "details": {
            "eventOwnerTeamId": 52,
            "losingPlayerId": 8475170,
            "winningPlayerId": 8476392,
            "xCoord": -20,
            "yCoord": 22,
            "zoneCode": "N"
        }
    },
    {
        "eventId": 303,
        "periodDescriptor": {
            "number": 2,
            "periodType": "REG",
            "maxRegulationPeriods": 3
        },
        "timeInPeriod": "05:01",
        "timeRemaining": "14:59",
        "situationCode": "1551",
        "homeTeamDefendingSide": "left",
        "typeCode": 502,
        "typeDescKey": "faceoff",
        "sortOrder": 345,
        "details": {
            "eventOwnerTeamId": 19,
            "losingPlayerId": 8476392,
            "winningPlayerId": 8480023,
            "xCoord": -69,
            "yCoord": -22,
            "zoneCode": "O"
        }
    },
    {
        "eventId": 305,
        "periodDescriptor": {
            "number": 2,
            "periodType": "REG",
            "maxRegulationPeriods": 3
        },
        "timeInPeriod": "07:05",
        "timeRemaining": "12:55",
        "situationCode": "1551",
        "homeTeamDefendingSide": "left",
        "typeCode": 502,
        "typeDescKey": "faceoff",
        "sortOrder": 366,
        "details": {
            "eventOwnerTeamId": 52,
            "losingPlayerId": 8480023,
            "winningPlayerId": 8476460,
            "xCoord": -69,
            "yCoord": -22,
            "zoneCode": "D"
        }
    },
    {
        "eventId": 504,
        "periodDescriptor": {
            "number": 2,
            "periodType": "REG",
            "maxRegulationPeriods": 3
        },
        "timeInPeriod": "07:27",
        "timeRemaining": "12:33",
        "situationCode": "1551",
        "homeTeamDefendingSide": "left",
        "typeCode": 502,
        "typeDescKey": "faceoff",
        "sortOrder": 371,
        "details": {
            "eventOwnerTeamId": 19,
            "losingPlayerId": 8480289,
            "winningPlayerId": 8476897,
            "xCoord": 0,
            "yCoord": 0,
            "zoneCode": "N"
        }
    },
    {
        "eventId": 505,
        "periodDescriptor": {
            "number": 2,
            "periodType": "REG",
            "maxRegulationPeriods": 3
        },
        "timeInPeriod": "08:58",
        "timeRemaining": "11:02",
        "situationCode": "1541",
        "homeTeamDefendingSide": "left",
        "typeCode": 502,
        "typeDescKey": "faceoff",
        "sortOrder": 393,
        "details": {
            "eventOwnerTeamId": 19,
            "losingPlayerId": 8476392,
            "winningPlayerId": 8480023,
            "xCoord": -69,
            "yCoord": 22,
            "zoneCode": "O"
        }
    },
    {
        "eventId": 308,
        "periodDescriptor": {
            "number": 2,
            "periodType": "REG",
            "maxRegulationPeriods": 3
        },
        "timeInPeriod": "10:23",
        "timeRemaining": "09:37",
        "situationCode": "1441",
        "homeTeamDefendingSide": "left",
        "typeCode": 502,
        "typeDescKey": "faceoff",
        "sortOrder": 409,
        "details": {
            "eventOwnerTeamId": 52,
            "losingPlayerId": 8475170,
            "winningPlayerId": 8476392,
            "xCoord": 69,
            "yCoord": 22,
            "zoneCode": "O"
        }
    },
    {
        "eventId": 310,
        "periodDescriptor": {
            "number": 2,
            "periodType": "REG",
            "maxRegulationPeriods": 3
        },
        "timeInPeriod": "12:11",
        "timeRemaining": "07:49",
        "situationCode": "1451",
        "homeTeamDefendingSide": "left",
        "typeCode": 502,
        "typeDescKey": "faceoff",
        "sortOrder": 426,
        "details": {
            "eventOwnerTeamId": 19,
            "losingPlayerId": 8476480,
            "winningPlayerId": 8480023,
            "xCoord": 69,
            "yCoord": -22,
            "zoneCode": "D"
        }
    },
    {
        "eventId": 312,
        "periodDescriptor": {
            "number": 2,
            "periodType": "REG",
            "maxRegulationPeriods": 3
        },
        "timeInPeriod": "14:32",
        "timeRemaining": "05:28",
        "situationCode": "1551",
        "homeTeamDefendingSide": "left",
        "typeCode": 502,
        "typeDescKey": "faceoff",
        "sortOrder": 458,
        "details": {
            "eventOwnerTeamId": 52,
            "losingPlayerId": 8480023,
            "winningPlayerId": 8476460,
            "xCoord": -69,
            "yCoord": 22,
            "zoneCode": "D"
        }
    },
    {
        "eventId": 314,
        "periodDescriptor": {
            "number": 2,
            "periodType": "REG",
            "maxRegulationPeriods": 3
        },
        "timeInPeriod": "15:23",
        "timeRemaining": "04:37",
        "situationCode": "1551",
        "homeTeamDefendingSide": "left",
        "typeCode": 502,
        "typeDescKey": "faceoff",
        "sortOrder": 471,
        "details": {
            "eventOwnerTeamId": 19,
            "losingPlayerId": 8476480,
            "winningPlayerId": 8476889,
            "xCoord": 69,
            "yCoord": -22,
            "zoneCode": "D"
        }
    },
    {
        "eventId": 316,
        "periodDescriptor": {
            "number": 2,
            "periodType": "REG",
            "maxRegulationPeriods": 3
        },
        "timeInPeriod": "16:27",
        "timeRemaining": "03:33",
        "situationCode": "1551",
        "homeTeamDefendingSide": "left",
        "typeCode": 502,
        "typeDescKey": "faceoff",
        "sortOrder": 478,
        "details": {
            "eventOwnerTeamId": 52,
            "losingPlayerId": 8475170,
            "winningPlayerId": 8476392,
            "xCoord": 69,
            "yCoord": -22,
            "zoneCode": "O"
        }
    },
    {
        "eventId": 322,
        "periodDescriptor": {
            "number": 3,
            "periodType": "REG",
            "maxRegulationPeriods": 3
        },
        "timeInPeriod": "00:00",
        "timeRemaining": "20:00",
        "situationCode": "1551",
        "homeTeamDefendingSide": "right",
        "typeCode": 502,
        "typeDescKey": "faceoff",
        "sortOrder": 526,
        "details": {
            "eventOwnerTeamId": 19,
            "losingPlayerId": 8476480,
            "winningPlayerId": 8476889,
            "xCoord": 0,
            "yCoord": 0,
            "zoneCode": "N"
        }
    },
    {
        "eventId": 325,
        "periodDescriptor": {
            "number": 3,
            "periodType": "REG",
            "maxRegulationPeriods": 3
        },
        "timeInPeriod": "01:51",
        "timeRemaining": "18:09",
        "situationCode": "1551",
        "homeTeamDefendingSide": "right",
        "typeCode": 502,
        "typeDescKey": "faceoff",
        "sortOrder": 548,
        "details": {
            "eventOwnerTeamId": 19,
            "losingPlayerId": 8476392,
            "winningPlayerId": 8475170,
            "xCoord": 20,
            "yCoord": -22,
            "zoneCode": "N"
        }
    },
    {
        "eventId": 327,
        "periodDescriptor": {
            "number": 3,
            "periodType": "REG",
            "maxRegulationPeriods": 3
        },
        "timeInPeriod": "02:35",
        "timeRemaining": "17:25",
        "situationCode": "1551",
        "homeTeamDefendingSide": "right",
        "typeCode": 502,
        "typeDescKey": "faceoff",
        "sortOrder": 560,
        "details": {
            "eventOwnerTeamId": 19,
            "losingPlayerId": 8482149,
            "winningPlayerId": 8480023,
            "xCoord": -69,
            "yCoord": -22,
            "zoneCode": "D"
        }
    },
    {
        "eventId": 507,
        "periodDescriptor": {
            "number": 3,
            "periodType": "REG",
            "maxRegulationPeriods": 3
        },
        "timeInPeriod": "03:09",
        "timeRemaining": "16:51",
        "situationCode": "1541",
        "homeTeamDefendingSide": "right",
        "typeCode": 502,
        "typeDescKey": "faceoff",
        "sortOrder": 565,
        "details": {
            "eventOwnerTeamId": 19,
            "losingPlayerId": 8476392,
            "winningPlayerId": 8475170,
            "xCoord": 69,
            "yCoord": 22,
            "zoneCode": "O"
        }
    },
    {
        "eventId": 329,
        "periodDescriptor": {
            "number": 3,
            "periodType": "REG",
            "maxRegulationPeriods": 3
        },
        "timeInPeriod": "06:01",
        "timeRemaining": "13:59",
        "situationCode": "1551",
        "homeTeamDefendingSide": "right",
        "typeCode": 502,
        "typeDescKey": "faceoff",
        "sortOrder": 604,
        "details": {
            "eventOwnerTeamId": 52,
            "losingPlayerId": 8475170,
            "winningPlayerId": 8476392,
            "xCoord": -69,
            "yCoord": 22,
            "zoneCode": "O"
        }
    },
    {
        "eventId": 331,
        "periodDescriptor": {
            "number": 3,
            "periodType": "REG",
            "maxRegulationPeriods": 3
        },
        "timeInPeriod": "06:30",
        "timeRemaining": "13:30",
        "situationCode": "1551",
        "homeTeamDefendingSide": "right",
        "typeCode": 502,
        "typeDescKey": "faceoff",
        "sortOrder": 609,
        "details": {
            "eventOwnerTeamId": 52,
            "losingPlayerId": 8477402,
            "winningPlayerId": 8476460,
            "xCoord": 69,
            "yCoord": -22,
            "zoneCode": "D"
        }
    },
    {
        "eventId": 508,
        "periodDescriptor": {
            "number": 3,
            "periodType": "REG",
            "maxRegulationPeriods": 3
        },
        "timeInPeriod": "07:05",
        "timeRemaining": "12:55",
        "situationCode": "1551",
        "homeTeamDefendingSide": "right",
        "typeCode": 502,
        "typeDescKey": "faceoff",
        "sortOrder": 618,
        "details": {
            "eventOwnerTeamId": 52,
            "losingPlayerId": 8476897,
            "winningPlayerId": 8480289,
            "xCoord": 0,
            "yCoord": 0,
            "zoneCode": "N"
        }
    },
    {
        "eventId": 333,
        "periodDescriptor": {
            "number": 3,
            "periodType": "REG",
            "maxRegulationPeriods": 3
        },
        "timeInPeriod": "07:14",
        "timeRemaining": "12:46",
        "situationCode": "1551",
        "homeTeamDefendingSide": "right",
        "typeCode": 502,
        "typeDescKey": "faceoff",
        "sortOrder": 620,
        "details": {
            "eventOwnerTeamId": 52,
            "losingPlayerId": 8476897,
            "winningPlayerId": 8481019,
            "xCoord": -20,
            "yCoord": -22,
            "zoneCode": "N"
        }
    },
    {
        "eventId": 335,
        "periodDescriptor": {
            "number": 3,
            "periodType": "REG",
            "maxRegulationPeriods": 3
        },
        "timeInPeriod": "08:35",
        "timeRemaining": "11:25",
        "situationCode": "1551",
        "homeTeamDefendingSide": "right",
        "typeCode": 502,
        "typeDescKey": "faceoff",
        "sortOrder": 634,
        "details": {
            "eventOwnerTeamId": 19,
            "losingPlayerId": 8476480,
            "winningPlayerId": 8476889,
            "xCoord": -69,
            "yCoord": -22,
            "zoneCode": "D"
        }
    },
    {
        "eventId": 337,
        "periodDescriptor": {
            "number": 3,
            "periodType": "REG",
            "maxRegulationPeriods": 3
        },
        "timeInPeriod": "11:16",
        "timeRemaining": "08:44",
        "situationCode": "1551",
        "homeTeamDefendingSide": "right",
        "typeCode": 502,
        "typeDescKey": "faceoff",
        "sortOrder": 670,
        "details": {
            "eventOwnerTeamId": 19,
            "losingPlayerId": 8476480,
            "winningPlayerId": 8476897,
            "xCoord": -69,
            "yCoord": -22,
            "zoneCode": "D"
        }
    },
    {
        "eventId": 339,
        "periodDescriptor": {
            "number": 3,
            "periodType": "REG",
            "maxRegulationPeriods": 3
        },
        "timeInPeriod": "12:22",
        "timeRemaining": "07:38",
        "situationCode": "1551",
        "homeTeamDefendingSide": "right",
        "typeCode": 502,
        "typeDescKey": "faceoff",
        "sortOrder": 688,
        "details": {
            "eventOwnerTeamId": 52,
            "losingPlayerId": 8480023,
            "winningPlayerId": 8476460,
            "xCoord": -69,
            "yCoord": -22,
            "zoneCode": "O"
        }
    },
    {
        "eventId": 341,
        "periodDescriptor": {
            "number": 3,
            "periodType": "REG",
            "maxRegulationPeriods": 3
        },
        "timeInPeriod": "12:27",
        "timeRemaining": "07:33",
        "situationCode": "1551",
        "homeTeamDefendingSide": "right",
        "typeCode": 502,
        "typeDescKey": "faceoff",
        "sortOrder": 691,
        "details": {
            "eventOwnerTeamId": 52,
            "losingPlayerId": 8480023,
            "winningPlayerId": 8476460,
            "xCoord": -69,
            "yCoord": -22,
            "zoneCode": "O"
        }
    },
    {
        "eventId": 343,
        "periodDescriptor": {
            "number": 3,
            "periodType": "REG",
            "maxRegulationPeriods": 3
        },
        "timeInPeriod": "14:14",
        "timeRemaining": "05:46",
        "situationCode": "1551",
        "homeTeamDefendingSide": "right",
        "typeCode": 502,
        "typeDescKey": "faceoff",
        "sortOrder": 716,
        "details": {
            "eventOwnerTeamId": 19,
            "losingPlayerId": 8476480,
            "winningPlayerId": 8475170,
            "xCoord": -69,
            "yCoord": -22,
            "zoneCode": "D"
        }
    },
    {
        "eventId": 345,
        "periodDescriptor": {
            "number": 3,
            "periodType": "REG",
            "maxRegulationPeriods": 3
        },
        "timeInPeriod": "16:31",
        "timeRemaining": "03:29",
        "situationCode": "1551",
        "homeTeamDefendingSide": "right",
        "typeCode": 502,
        "typeDescKey": "faceoff",
        "sortOrder": 745,
        "details": {
            "eventOwnerTeamId": 52,
            "losingPlayerId": 8476897,
            "winningPlayerId": 8476480,
            "xCoord": 20,
            "yCoord": -22,
            "zoneCode": "N"
        }
    },
    {
        "eventId": 347,
        "periodDescriptor": {
            "number": 3,
            "periodType": "REG",
            "maxRegulationPeriods": 3
        },
        "timeInPeriod": "17:58",
        "timeRemaining": "02:02",
        "situationCode": "0651",
        "homeTeamDefendingSide": "right",
        "typeCode": 502,
        "typeDescKey": "faceoff",
        "sortOrder": 758,
        "details": {
            "eventOwnerTeamId": 52,
            "losingPlayerId": 8480023,
            "winningPlayerId": 8476460,
            "xCoord": 69,
            "yCoord": -22,
            "zoneCode": "D"
        }
    },
    {
        "eventId": 350,
        "periodDescriptor": {
            "number": 3,
            "periodType": "REG",
            "maxRegulationPeriods": 3
        },
        "timeInPeriod": "18:16",
        "timeRemaining": "01:44",
        "situationCode": "0651",
        "homeTeamDefendingSide": "right",
        "typeCode": 502,
        "typeDescKey": "faceoff",
        "sortOrder": 762,
        "details": {
            "eventOwnerTeamId": 19,
            "losingPlayerId": 8476460,
            "winningPlayerId": 8475170,
            "xCoord": 69,
            "yCoord": 22,
            "zoneCode": "O"
        }
    },
    {
        "eventId": 802,
        "periodDescriptor": {
            "number": 3,
            "periodType": "REG",
            "maxRegulationPeriods": 3
        },
        "timeInPeriod": "19:06",
        "timeRemaining": "00:54",
        "situationCode": "0651",
        "homeTeamDefendingSide": "right",
        "typeCode": 502,
        "typeDescKey": "faceoff",
        "sortOrder": 768,
        "details": {
            "eventOwnerTeamId": 52,
            "losingPlayerId": 8480023,
            "winningPlayerId": 8476392,
            "xCoord": 69,
            "yCoord": -22,
            "zoneCode": "D"
        }
    },
    {
        "eventId": 805,
        "periodDescriptor": {
            "number": 3,
            "periodType": "REG",
            "maxRegulationPeriods": 3
        },
        "timeInPeriod": "19:34",
        "timeRemaining": "00:26",
        "situationCode": "0651",
        "homeTeamDefendingSide": "right",
        "typeCode": 502,
        "typeDescKey": "faceoff",
        "sortOrder": 775,
        "details": {
            "eventOwnerTeamId": 19,
            "losingPlayerId": 8476460,
            "winningPlayerId": 8475170,
            "xCoord": 69,
            "yCoord": 22,
            "zoneCode": "O"
        }
    },
    {
        "eventId": 807,
        "periodDescriptor": {
            "number": 3,
            "periodType": "REG",
            "maxRegulationPeriods": 3
        },
        "timeInPeriod": "19:36",
        "timeRemaining": "00:24",
        "situationCode": "0651",
        "homeTeamDefendingSide": "right",
        "typeCode": 502,
        "typeDescKey": "faceoff",
        "sortOrder": 778,
        "details": {
            "eventOwnerTeamId": 52,
            "losingPlayerId": 8475170,
            "winningPlayerId": 8476460,
            "xCoord": 69,
            "yCoord": 22,
            "zoneCode": "D"
        }
    },
    {
        "eventId": 808,
        "periodDescriptor": {
            "number": 3,
            "periodType": "REG",
            "maxRegulationPeriods": 3
        },
        "timeInPeriod": "19:51",
        "timeRemaining": "00:09",
        "situationCode": "1551",
        "homeTeamDefendingSide": "right",
        "typeCode": 502,
        "typeDescKey": "faceoff",
        "sortOrder": 782,
        "details": {
            "eventOwnerTeamId": 19,
            "losingPlayerId": 8480289,
            "winningPlayerId": 8476897,
            "xCoord": 0,
            "yCoord": 0,
            "zoneCode": "N"
        }
    }
]